fastlisaresponse_cuda11x.libs/libcudart-d0da41ae.so.11.8.89
fastlisaresponse_backend_cuda11x/git_version.py
fastlisaresponse_backend_cuda11x/responselisa.cpython-311-x86_64-linux-gnu.so
fastlisaresponse/_version.py
fastlisaresponse/response.py
fastlisaresponse/git_version.py.in
fastlisaresponse/__init__.py
fastlisaresponse/cutils/__init__.py
fastlisaresponse/utils/parallelbase.py
fastlisaresponse/utils/utility.py
fastlisaresponse/utils/citations.py
fastlisaresponse/utils/exceptions.py
fastlisaresponse/utils/config.py
fastlisaresponse/utils/__init__.py
fastlisaresponse_cuda11x-1.1.11.dist-info/WHEEL
fastlisaresponse_cuda11x-1.1.11.dist-info/METADATA
fastlisaresponse_cuda11x-1.1.11.dist-info/RECORD
lib64/python./site-packages/fastlisaresponse/responselisa.cpython-311-x86_64-linux-gnu.so
