Metadata-Version: 2.2
Name: fastlisaresponse-cuda11x
Version: 1.1.11
Summary: GPU-accelerated LISA Response Function
Author-Email: Michael Katz <mikekatz04@gmail.com>
Classifier: Environment :: GPU :: NVIDIA CUDA
Classifier: License :: OSI Approved :: Apache Software License
Classifier: Natural Language :: English
Classifier: Programming Language :: C++
Classifier: Programming Language :: Cython
Classifier: Programming Language :: Python :: 3 :: Only
Classifier: Programming Language :: Python :: 3.9
Classifier: Programming Language :: Python :: 3.10
Classifier: Programming Language :: Python :: 3.11
Classifier: Programming Language :: Python :: 3.12
Classifier: Programming Language :: Python :: 3.13
Requires-Python: >=3.9
Requires-Dist: lisaanalysistools>=1.1.16
Requires-Dist: exceptiongroup; python_version < "3.11"
Requires-Dist: h5py<3.15
Requires-Dist: matplotlib
Requires-Dist: gpubackendtools
Requires-Dist: jsonschema
Requires-Dist: lisaconstants
Requires-Dist: multispline
Requires-Dist: numba
Requires-Dist: numpy
Requires-Dist: nvidia-ml-py
Requires-Dist: platformdirs
Requires-Dist: pydantic
Requires-Dist: pyyaml
Requires-Dist: requests
Requires-Dist: rich
Requires-Dist: scipy
Requires-Dist: tqdm
Requires-Dist: wrapt
Requires-Dist: cupy-cuda11x
Requires-Dist: fastlisaresponse==1.1.11
Provides-Extra: doc
Requires-Dist: ipykernel; extra == "doc"
Requires-Dist: ipython; extra == "doc"
Requires-Dist: ipywidgets; extra == "doc"
Requires-Dist: myst-parser; extra == "doc"
Requires-Dist: nbsphinx; extra == "doc"
Requires-Dist: pypandoc; extra == "doc"
Requires-Dist: sphinx; extra == "doc"
Requires-Dist: sphinx-rtd-theme; extra == "doc"
Requires-Dist: sphinx-tippy; extra == "doc"
Requires-Dist: astropy; extra == "doc"
Provides-Extra: sampling
Requires-Dist: eryn; extra == "sampling"
Requires-Dist: astropy; extra == "sampling"
Provides-Extra: testing
Requires-Dist: matplotlib; extra == "testing"
Requires-Dist: astropy; extra == "testing"
